pyqthotkey/__init__.py
pyqthotkey/hotkey_picker.py
pyqthotkey-3.0.0.dist-info/LICENSE
pyqthotkey-3.0.0.dist-info/METADATA
pyqthotkey-3.0.0.dist-info/WHEEL
pyqthotkey-3.0.0.dist-info/top_level.txt
pyqthotkey-3.0.0.dist-info/RECORD
