Metadata-Version: 2.1
Name: pyqthotkey
Version: 3.0.0
Summary: A simple and customizable hotkey picker widget for PyQt and PySide
Home-page: https://github.com/niklashenning/pyqthotkey
Author: Niklas Henning
Author-email: business@niklashenning.com
License: MIT
Keywords: python,qt,pyqt,pyside,hotkey,hotkey picker,keyboard
Classifier: Programming Language :: Python :: 3
Classifier: Operating System :: OS Independent
Classifier: License :: OSI Approved :: MIT License
Requires-Python: >=3.7
License-File: LICENSE
Requires-Dist: QtPy >=2.4.1
